[{"Cliente: ":"asdasdd","Preço: ":[80.0,80.0,80.0,80.0],"Unidade: ":["KG","KG","KG","KG"],"Produto: ":["Torta","Torta","Torta","Torta"],"Sabor: ":["Torta Horlandesa","Torta Horlandesa","Torta Horlandesa","Torta Horlandesa"],"qtd: ":[1,1,1,1],"CPF: ":"11337142859","NF: ":"101020171","Total: ":320.0},{"Cliente: ":"asdasdd","Preço: ":[80.0,80.0,80.0,80.0],"Unidade: ":["KG","KG","KG","KG"],"Produto: ":["Torta","Torta","Torta","Torta"],"Sabor: ":["Torta Horlandesa","Torta Horlandesa","Torta Horlandesa","Torta Horlandesa"],"qtd: ":[1,1,1,1],"CPF: ":"11337142859","NF: ":"101020172","Total: ":320.0},{"Cliente: ":null,"Preço: ":[80.0,80.0],"Unidade: ":["KG","KG"],"Produto: ":["Torta","Torta"],"Sabor: ":["Torta Horlandesa","Torta Horlandesa"],"qtd: ":[1,1],"CPF: ":null,"NF: ":"101020173","Total: ":160.0},{"Cliente: ":null,"Preço: ":[80.0,80.0,80.0],"Unidade: ":["KG","KG","KG"],"Produto: ":["Torta","Torta","Torta"],"Sabor: ":["Torta morango","Torta morango","Torta morango"],"qtd: ":[1,1,1],"CPF: ":null,"NF: ":"101020174","Total: ":240.0},{"Cliente: ":"Joao","Preço: ":[80.0,80.0],"Unidade: ":["KG","KG"],"Produto: ":["Torta","Torta"],"Sabor: ":["Torta morango","Torta maça"],"qtd: ":[1,1],"CPF: ":"41275995888","NF: ":"101020175","Total: ":160.0},{"Cliente: ":"Luiz Rodrigo","Preço: ":[2.0,80.0,80.0],"Unidade: ":["Unidade","KG","KG"],"Produto: ":["Bolo de pote","Torta","Torta"],"Sabor: ":["abacaxi","Torta morango","Torta morango"],"qtd: ":[1,1,3],"CPF: ":"40568697820","NF: ":"111020176","Total: ":322.0},{"Cliente: ":"Lucas ","Preço: ":[80.0],"Unidade: ":["KG"],"Produto: ":["Torta"],"Sabor: ":["Torta Horlandesa"],"qtd: ":[2],"CPF: ":"43249142816","NF: ":"111020177","Total: ":160.0}]